calculation/__init__.py
calculation/apps.py
calculation/widgets.py
calculation/static/calculation/js/calculation.js
django_calculation-1.0.0.dist-info/LICENSE
django_calculation-1.0.0.dist-info/METADATA
django_calculation-1.0.0.dist-info/WHEEL
django_calculation-1.0.0.dist-info/top_level.txt
django_calculation-1.0.0.dist-info/RECORD
